autonlp/__init__.py
autonlp/audio_utils.py
autonlp/autonlp.py
autonlp/config.py
autonlp/evaluate.py
autonlp/languages.py
autonlp/metrics.py
autonlp/model.py
autonlp/project.py
autonlp/splits.py
autonlp/tasks.py
autonlp/utils.py
autonlp/validation.py
autonlp/cli/__init__.py
autonlp/cli/autonlp.py
autonlp/cli/benchmark.py
autonlp/cli/common.py
autonlp/cli/create_project.py
autonlp/cli/estimator.py
autonlp/cli/evaluate.py
autonlp/cli/list_projects.py
autonlp/cli/login.py
autonlp/cli/metrics.py
autonlp/cli/predict.py
autonlp/cli/project_info.py
autonlp/cli/train.py
autonlp/cli/upload.py
autonlp-0.3.7.data/scripts/autonlp
autonlp-0.3.7.dist-info/LICENSE
autonlp-0.3.7.dist-info/METADATA
autonlp-0.3.7.dist-info/WHEEL
autonlp-0.3.7.dist-info/entry_points.txt
autonlp-0.3.7.dist-info/top_level.txt
autonlp-0.3.7.dist-info/RECORD
