Metadata-Version: 2.1
Name: autonlp
Version: 0.3.7
Summary: HuggingFace/AutoNLP
Home-page: https://github.com/huggingface/autonlp
Author: HuggingFace Inc.
Author-email: abhishek@huggingface.co
License: Apache 2.0
Download-URL: https://github.com/huggingface/autonlp/tags
Keywords: automl autonlp huggingface
Platform: UNKNOWN
Classifier: Development Status :: 5 - Production/Stable
Classifier: Intended Audience :: Developers
Classifier: Intended Audience :: Education
Classifier: Intended Audience :: Science/Research
Classifier: License :: OSI Approved :: Apache Software License
Classifier: Operating System :: OS Independent
Classifier: Programming Language :: Python :: 3
Classifier: Programming Language :: Python :: 3.6
Classifier: Programming Language :: Python :: 3.7
Classifier: Topic :: Scientific/Engineering :: Artificial Intelligence
Requires-Dist: loguru (==0.5.3)
Requires-Dist: requests (==2.25.1)
Requires-Dist: tqdm (==4.49)
Requires-Dist: prettytable (==2.0.0)
Requires-Dist: huggingface-hub (==0.0.12)
Requires-Dist: datasets (==1.11.0)
Provides-Extra: dev
Requires-Dist: loguru (==0.5.3) ; extra == 'dev'
Requires-Dist: requests (==2.25.1) ; extra == 'dev'
Requires-Dist: tqdm (==4.49) ; extra == 'dev'
Requires-Dist: prettytable (==2.0.0) ; extra == 'dev'
Requires-Dist: huggingface-hub (==0.0.12) ; extra == 'dev'
Requires-Dist: datasets (==1.11.0) ; extra == 'dev'
Requires-Dist: black ; extra == 'dev'
Requires-Dist: isort ; extra == 'dev'
Requires-Dist: flake8 (==3.7.9) ; extra == 'dev'
Requires-Dist: pytest ; extra == 'dev'
Provides-Extra: docs
Requires-Dist: loguru (==0.5.3) ; extra == 'docs'
Requires-Dist: requests (==2.25.1) ; extra == 'docs'
Requires-Dist: tqdm (==4.49) ; extra == 'docs'
Requires-Dist: prettytable (==2.0.0) ; extra == 'docs'
Requires-Dist: huggingface-hub (==0.0.12) ; extra == 'docs'
Requires-Dist: datasets (==1.11.0) ; extra == 'docs'
Requires-Dist: recommonmark ; extra == 'docs'
Requires-Dist: sphinx (==3.1.2) ; extra == 'docs'
Requires-Dist: sphinx-markdown-tables ; extra == 'docs'
Requires-Dist: sphinx-rtd-theme (==0.4.3) ; extra == 'docs'
Requires-Dist: sphinx-copybutton ; extra == 'docs'
Provides-Extra: quality
Requires-Dist: loguru (==0.5.3) ; extra == 'quality'
Requires-Dist: requests (==2.25.1) ; extra == 'quality'
Requires-Dist: tqdm (==4.49) ; extra == 'quality'
Requires-Dist: prettytable (==2.0.0) ; extra == 'quality'
Requires-Dist: huggingface-hub (==0.0.12) ; extra == 'quality'
Requires-Dist: datasets (==1.11.0) ; extra == 'quality'
Requires-Dist: black ; extra == 'quality'
Requires-Dist: isort ; extra == 'quality'
Requires-Dist: flake8 (==3.7.9) ; extra == 'quality'
